rotastellar_intel/__init__.py
rotastellar_intel/conjunctions.py
rotastellar_intel/patterns.py
rotastellar_intel/tle.py
rotastellar_intel/tracker.py
rotastellar_intel-0.1.1.dist-info/METADATA
rotastellar_intel-0.1.1.dist-info/WHEEL
rotastellar_intel-0.1.1.dist-info/licenses/LICENSE
rotastellar_intel-0.1.1.dist-info/RECORD
