Metadata-Version: 2.4
Name: rotastellar-intel
Version: 0.1.1
Summary: Orbital intelligence and space situational awareness tools
Project-URL: Homepage, https://rotastellar.com/products/orbital-intelligence
Project-URL: Documentation, https://rotastellar.com/docs/intel
Project-URL: Repository, https://github.com/rotastellar/rotastellar-python
Author-email: Subhadip Mitra <subhadipmitra@rotastellar.com>, RotaStellar Research <research@rotastellar.com>
Maintainer-email: Subhadip Mitra <subhadipmitra@rotastellar.com>, RotaStellar Research <research@rotastellar.com>
License: MIT
License-File: LICENSE
Keywords: conjunction-analysis,orbital-intelligence,satellite-tracking,sgp4,space,space-situational-awareness,tle
Classifier: Development Status :: 4 - Beta
Classifier: Intended Audience :: Developers
Classifier: Intended Audience :: Science/Research
Classifier: License :: OSI Approved :: MIT License
Classifier: Operating System :: OS Independent
Classifier: Programming Language :: Python :: 3
Classifier: Programming Language :: Python :: 3.9
Classifier: Programming Language :: Python :: 3.10
Classifier: Programming Language :: Python :: 3.11
Classifier: Programming Language :: Python :: 3.12
Classifier: Topic :: Scientific/Engineering :: Astronomy
Classifier: Topic :: Scientific/Engineering :: GIS
Classifier: Typing :: Typed
Requires-Python: >=3.9
Requires-Dist: rotastellar>=0.1.0
Provides-Extra: dev
Requires-Dist: mypy>=1.0; extra == 'dev'
Requires-Dist: pytest-asyncio>=0.21; extra == 'dev'
Requires-Dist: pytest>=7.0; extra == 'dev'
Provides-Extra: sgp4
Requires-Dist: sgp4>=2.22; extra == 'sgp4'
